ginggar
